LFPsimpy/LFPsimpy.hoc
LFPsimpy/__init__.py
LFPsimpy-0.1.1.dist-info/METADATA
LFPsimpy-0.1.1.dist-info/RECORD
LFPsimpy-0.1.1.dist-info/WHEEL
LFPsimpy-0.1.1.dist-info/top_level.txt
tests/__init__.py
tests/test_all.py
