Metadata-Version: 2.1
Name: LFPsimpy
Version: 0.1.1
Summary: Zero-model-modification, MPI-compatible Python package for computing NEURON simulator model local field potentials (LFPs)
Home-page: https://github.com/justasb/LFPsimpy
Author: Justas Birgiolas
Author-email: justas@asu.edu
License: UNKNOWN
Platform: UNKNOWN
Classifier: Programming Language :: Python :: 3
Classifier: License :: OSI Approved :: MIT License
Classifier: Operating System :: OS Independent
